Metadata-Version: 1.2
Name: catscii
Version: 19.8.1
Summary: A simple catalog query tool in python
Home-page: UNKNOWN
Author: Romain Thomas
License: UNKNOWN
Platform: UNKNOWN
Requires-Python: >=3.6
